mekuria_package/__init__.py
Mekuria_package-0.0.1.dist-info/LICENSE
Mekuria_package-0.0.1.dist-info/METADATA
Mekuria_package-0.0.1.dist-info/WHEEL
Mekuria_package-0.0.1.dist-info/top_level.txt
Mekuria_package-0.0.1.dist-info/RECORD
