Metadata-Version: 2.1
Name: Mekuria-package
Version: 0.0.1
Summary: an Example Package for Mekuria.
Home-page: https://repl.it/@meki2020/Mekuria-package
Author: Mekuria Tegegne
Author-email: mekuriategegne@gmail.com
License: UNKNOWN
Platform: UNKNOWN
Classifier: Programming Language :: Python :: 3
Classifier: License :: OSI Approved :: MIT License
Classifier: Operating System :: OS Independent
Requires-Python: >=3.6
